logagg_collector/__init__.py
logagg_collector/collector.py
logagg_collector/collector_command.py
logagg_collector/formatters.py
logagg_fs/__init__.py
logagg_fs/fs.py
logagg_fs/mirrorfs.py
logagg_collector-0.0.1.dist-info/METADATA
logagg_collector-0.0.1.dist-info/WHEEL
logagg_collector-0.0.1.dist-info/dependency_links.txt
logagg_collector-0.0.1.dist-info/entry_points.txt
logagg_collector-0.0.1.dist-info/top_level.txt
logagg_collector-0.0.1.dist-info/RECORD
